libhess.cp38-win_amd64.pyd
hess/__init__.py
hess/hess.py
HESS-0.0.2.dist-info/LICENSE
HESS-0.0.2.dist-info/METADATA
HESS-0.0.2.dist-info/WHEEL
HESS-0.0.2.dist-info/top_level.txt
HESS-0.0.2.dist-info/RECORD
