Metadata-Version: 2.1
Name: HESS
Version: 0.0.2
Summary: HESS black-box algorithm from http://www.peqnp.com
Home-page: http://www.peqnp.com
Author: Oscar Riveros
Author-email: contact@peqnp.science
License: Copyright (c) 2012-2020 Oscar Riveros. All rights reserved.
Keywords: IA,Optimization,Deep Learning
Platform: UNKNOWN
